{
    "status": "ok",
    "totalResults": 82,
    "articles": [
        {
            "source": {
                "id": "the-times-of-india",
                "name": "The Times of India"
            },
            "author": "Riya Sharma",
            "title": "Ahead of Market: 10 things that will decide stock market action on Thursday",
            "description": "Indian markets extended gains for the sixth session as Nifty and Sensex closed higher, driven by optimism over India\u2013US trade talks, potential GST cuts, and expectations of a U.S. Fed rate cut.",
            "url": "https://economictimes.indiatimes.com/markets/stocks/news/ahead-of-market-10-things-that-will-decide-stock-market-action-on-thursday/articleshow/123812646.cms",
            "urlToImage": "https://img.etimg.com/thumb/msid-123812687,width-1200,height-630,imgsize-54240,overlay-etmarkets/articleshow.jpg",
            "publishedAt": "2025-09-10T15:43:31Z",
            "content": "The Indian market ended higher on Wednesday, with the Nifty notching a sixth consecutive gain, after U.S. President Donald Trump said his administration is continuing negotiations to address trade ba\u2026 [+4477 chars]"
        },
        {
            "source": {
                "id": null,
                "name": "BusinessLine"
            },
            "author": "Team BL, KS Badri Narayanan",
            "title": "Share Market Highlights: Markets extend gains; IT, capital goods drive rally as trade talks cheer sentiment",
            "description": "Sensex, Nifty updates on 10 Septemebr 2025: Equity benchmarks ended higher on Wednesday, buoyed by optimism over India-US trade talks and hopes of a US Federal Reserve rate cut next week. The Sensex rose 323.83 points (0.40%) to 81,425.15, while the Nifty gai\u2026",
            "url": "https://www.thehindubusinessline.com/markets/stock-market-highlights-10-sept-2025/article70030918.ece",
            "urlToImage": "https://bl-i.thgim.com/public/incoming/5iltxi/article70000180.ece/alternates/LANDSCAPE_1200/IMG_PO16_Candle_2_2_1_GTE482N4.jpg",
            "publishedAt": "2025-09-10T01:07:45Z",
            "content": "<li></li>\r\nSeptember 10, 2025 16:32The live blog is now closed\r\n<li></li>\r\nSeptember 10, 2025 15:51Stock market live today: AU Small Finance Bank announces passing of CFO Vimal Jain due to cardiac ar\u2026 [+61374 chars]"
        },
        {
            "source": {
                "id": "the-times-of-india",
                "name": "The Times of India"
            },
            "author": "Riya Sharma",
            "title": "Ahead of Market: 10 things that will decide stock market action on Wednesday",
            "description": "Indian markets ended higher as Infosys\u2019 share buyback announcement boosted IT stocks, while consumer discretionary gained on GST optimism. Expectations of a U.S. Fed rate cut further lifted investor sentiment, with Sensex closing at 81,101 and Nifty at 24,869.",
            "url": "https://economictimes.indiatimes.com/markets/stocks/news/ahead-of-market-10-things-that-will-decide-stock-market-action-on-wednesday/articleshow/123790262.cms",
            "urlToImage": "https://img.etimg.com/thumb/msid-123790255,width-1200,height-630,imgsize-54240,overlay-etmarkets/articleshow.jpg",
            "publishedAt": "2025-09-09T15:58:02Z",
            "content": "The Indian market ended higher on Tuesday, as Infosys announcement of a potential share buyback sparked a rally in IT stocks. Consumer discretionary shares also advanced amid optimism over broad cuts\u2026 [+4561 chars]"
        },
        {
            "source": {
                "id": null,
                "name": "Economictimes.com"
            },
            "author": "TIL Creatives",
            "title": "Out of favour! Wipro, Asian Paints among 5 stocks with highest \u2018sell\u2019 calls in Nifty",
            "description": "Several prominent Indian stocks, including Wipro and Asian Paints, are currently facing strong sell recommendations from analysts. Data indicates bearish sentiment dominating IndusInd Bank and Dr. Reddy's Labs as well. Despite the caution, Tech Mahindra and A\u2026",
            "url": "https://m.economictimes.com/markets/stocks/news/out-of-favour-wipro-asian-paints-among-5-stocks-with-highest-sell-calls-in-nifty/exit-rush/slideshow/123780610.cms",
            "urlToImage": "https://img.etimg.com/thumb/msid-123780610,width-1070,height-580,overlay-etmarkets/slideshow.jpg",
            "publishedAt": "2025-09-09T06:58:04Z",
            "content": "The paint giant has 8 strong sell and 7 sell calls. But 10 analysts back it with buys, and expect up to 5% forward upside.\r\n(Disclaimer: Recommendations, suggestions, views and opinions given by the \u2026 [+77 chars]"
        },
        {
            "source": {
                "id": null,
                "name": "BusinessLine"
            },
            "author": "Team BL, KS Badri Narayanan",
            "title": "Share Market Highlights: Sensex rises 314 pts, Nifty tops 24,850; Infosys jumps 5% on buyback buzz",
            "description": "Sensex, Nifty updates on 9 Sept 2025: The Sensex gained 314 points to close at 81,101 and the Nifty ended 95 points higher at 24,869 on Tuesday, supported by IT stocks and hopes of a U.S. Fed rate cut. Infosys surged over 5% after announcing a board meet to c\u2026",
            "url": "https://www.thehindubusinessline.com/markets/stock-market-highlights-9-september-2025/article70026610.ece",
            "urlToImage": "https://bl-i.thgim.com/public/incoming/8bfcpv/article70021800.ece/alternates/LANDSCAPE_1200/PO_Candle_chart.jpg",
            "publishedAt": "2025-09-09T01:28:26Z",
            "content": "<li></li>\r\nSeptember 9, 2025 15:39CLOSING BELL: Sensex settled 314.02 pts or 0.39% higher at 81,101.32, and Nifty 50 ended with 95.45 pts or 0.39% gains at 24,868.60\r\n<li></li>\r\nSeptember 9, 2025 15:\u2026 [+36523 chars]"
        },
        {
            "source": {
                "id": null,
                "name": "BusinessLine"
            },
            "author": "Madhu Balaji",
            "title": "Sensex, Nifty climb on GST relief, auto & metal stocks drive rally",
            "description": "The momentum was led by auto and metal stocks, with Tata Motors, Tata Steel, and JSW Steel advancing sharply, reflecting improved investor sentiment and broad-based buying across segments",
            "url": "https://www.thehindubusinessline.com/markets/top-gainers-losers-mid-day-8th-sep-2025-sensex-nifty-climb-on-gst-relief-auto-metal-stocks-drive-rally/article70025092.ece",
            "urlToImage": "https://bl-i.thgim.com/public/incoming/oxgg2t/article70022282.ece/alternates/LANDSCAPE_1200/Stock%20market%20live%20today.jpg",
            "publishedAt": "2025-09-08T07:36:12Z",
            "content": "Domestic benchmark indices Sensex and Nifty 50 gained on the back of GST relief measures and hopes of a US Federal Reserve rate cut. \r\nAfter rising above 390 pts, Sensex traded 361.83 pts or 0.45 per\u2026 [+2172 chars]"
        },
        {
            "source": {
                "id": null,
                "name": "BusinessLine"
            },
            "author": "Akhil Nallamuthu & BL Research Bureau",
            "title": "Nifty Bank Prediction Today \u2013 September 8, 2025: Nifty Bank futures: Resistance ahead",
            "description": "Nifty Bank index opens with gap-up, showing bullish bias with top gainers and losers, facing resistance at 54,500.",
            "url": "https://www.thehindubusinessline.com/portfolio/technical-analysis/nifty-bank-prediction-today-september-8-2025-nifty-bank-futures-resistance-ahead/article70024772.ece",
            "urlToImage": "https://bl-i.thgim.com/public/incoming/prc4kj/article70024791.ece/alternates/LANDSCAPE_1200/PO30_Candlestick_graph.jpg",
            "publishedAt": "2025-09-08T05:19:41Z",
            "content": "Nifty Bank index opened todays session with a gap-up at 54,215 compared to Fridays close of 54,115. It is now hovering around 54,120.\r\nThe advance/decline ratio stands at 8/4, showing a bullish bias.\u2026 [+1486 chars]"
        },
        {
            "source": {
                "id": null,
                "name": "BusinessLine"
            },
            "author": "KS Badri Narayanan, Team BL",
            "title": "Share Market Highlights: Sensex, Nifty end higher; autos and steel shine, IT drags",
            "description": "Sensex, Nifty updates on 8 Sept 2025: The Sensex ended marginally higher on Monday, rising 76.54 points, or 0.09%, to close at 80,787.30 after touching an intraday high of 81,171.38. The Nifty 50 gained 32.15 points, or 0.13%, to settle at 24,773.15. Gains we\u2026",
            "url": "https://www.thehindubusinessline.com/markets/stock-market-highlights-8-september-2025/article69796834.ece",
            "urlToImage": "https://bl-i.thgim.com/public/incoming/oxgg2t/article70022282.ece/alternates/LANDSCAPE_1200/Stock%20market%20live%20today.jpg",
            "publishedAt": "2025-09-08T01:25:12Z",
            "content": "<li></li>\r\nSeptember 8, 2025 16:01Corporate announcement: Concord Control Systems announces 3:5 bonus share issue\r\nConcord Control Systems Limited (CCL), Indias leading manufacturer of embedded elect\u2026 [+46003 chars]"
        },
        {
            "source": {
                "id": null,
                "name": "Digitalocean.com"
            },
            "author": "Sanjay Agarwala",
            "title": "do you accept debit cards?",
            "description": "Do you not accept Debit card payments?I just tried to pay using my business account business debit card, and it would not work. What is more i got a pop \u2026",
            "url": "https://www.digitalocean.com/community/questions/do-you-accept-debit-cards",
            "urlToImage": "https://www.digitalocean.com/_next/static/media/social-share-default.e8530e9e.jpeg",
            "publishedAt": "2025-09-07T11:32:02Z",
            "content": "Credit and debit cards. We accept Visa, MasterCard, American Express, Discover, UnionPay, Diners Club, and JCB credit cards.\r\nCredit and debit cards from India need to be enabled for international tr\u2026 [+192 chars]"
        },
        {
            "source": {
                "id": null,
                "name": "BusinessLine"
            },
            "author": "BL Mumbai Bureau",
            "title": "IndusInd Bank \u2018categorically rejects\u2019 allegations of fraud cover-up by chairman",
            "description": "IndusInd Bank rejects allegations of accounting irregularities, denies Chairman's involvement, and cooperates with regulators for investigation.",
            "url": "https://www.thehindubusinessline.com/money-and-banking/indusind-bank-categorically-rejects-allegations-of-fraud-cover-up-by-chairman/article70012896.ece",
            "urlToImage": "https://bl-i.thgim.com/public/incoming/2xixp7/article70013117.ece/alternates/LANDSCAPE_1200/2025-08-25T101155Z_123478976_RC296AAJV870_RTRMADP_3_INDUSIND-BANK-CEO.JPG",
            "publishedAt": "2025-09-04T15:12:49Z",
            "content": "IndusInd Bank today, said it categorically rejects allegation made by former bank CFO Gobind Jain that the banks Chairman Sunil Mehta was involved in covering up accounting irregularities that caused\u2026 [+1409 chars]"
        },
        {
            "source": {
                "id": "the-times-of-india",
                "name": "The Times of India"
            },
            "author": "Riya Sharma",
            "title": "Ahead of Market: 10 things that will decide stock market action on Friday",
            "description": "Indian markets ended higher on Thursday as GST reforms supported consumption, while US tariff concerns lingered. Nifty closed at 24,734 and Sensex at 80,718, with active trading in stocks like Ola Electric, Mahindra & Mahindra, Bajaj Finance, and Reliance ami\u2026",
            "url": "https://economictimes.indiatimes.com/markets/stocks/news/ahead-of-market-10-things-that-will-decide-stock-market-action-on-friday/articleshow/123701934.cms",
            "urlToImage": "https://img.etimg.com/thumb/msid-123701952,width-1200,height-630,imgsize-110642,overlay-etmarkets/articleshow.jpg",
            "publishedAt": "2025-09-04T14:57:49Z",
            "content": "The Indian market ended higher on Thursday after the government trimmed levies on a range of goods in a Goods and Services Tax (GST) overhaul aimed at spurring consumption ahead of the festive season\u2026 [+3914 chars]"
        },
        {
            "source": {
                "id": null,
                "name": "BusinessLine"
            },
            "author": "Anupama Ghosh",
            "title": "GST reforms fail to sustain market rally as Sensex retreats 650 points from day\u2019s high",
            "description": "The Sensex closed at 80,718.01, up just 150.30 points (0.19%), while the Nifty settled at 24,734.30, gaining a modest 19.25 points (0.08%) after retreating over 650 points from intraday highs",
            "url": "https://www.thehindubusinessline.com/markets/gst-reforms-fail-to-sustain-market-rally-as-sensex-retreats-650-points-from-days-high/article70012000.ece",
            "urlToImage": "https://bl-i.thgim.com/public/incoming/ivek6x/article70007848.ece/alternates/LANDSCAPE_1200/IMG_PO10_carrying_graph_2_1_FTEOCNG2.jpg",
            "publishedAt": "2025-09-04T12:28:51Z",
            "content": "Markets witnessed a dramatic reversal on Wednesday as benchmark indices surrendered most of their early gains despite the government announcing sweeping GST reforms. \r\nThe Sensex closed at 80,718.01,\u2026 [+5127 chars]"
        },
        {
            "source": {
                "id": null,
                "name": "BusinessLine"
            },
            "author": "Anupama Ghosh",
            "title": "Markets pare gains as GST reform momentum fades by midday",
            "description": "Markets trimmed earlier gains by midday on Thursday, with the Sensex and Nifty giving up much of their morning rally despite positive sentiment around the GST Council\u2019s sweeping tax reforms announced the previous day.",
            "url": "https://www.thehindubusinessline.com/markets/stock-markets/markets-pare-gains-as-gst-reform-momentum-fades-by-midday/article70011228.ece",
            "urlToImage": "https://bl-i.thgim.com/public/incoming/i6i26o/article70011268.ece/alternates/LANDSCAPE_1200/PO20_Abstract_chart.jpg",
            "publishedAt": "2025-09-04T07:41:52Z",
            "content": "Markets trimmed earlier gains by midday on Thursday, with the Sensex and Nifty giving up much of their morning rally despite positive sentiment around the GST Councils sweeping tax reforms announced \u2026 [+2662 chars]"
        },
        {
            "source": {
                "id": null,
                "name": "BusinessLine"
            },
            "author": "Anupama Ghosh",
            "title": "GST 2.0 reforms drive market rally as Nifty eyes 25,000 mark",
            "description": "The Nifty 50 started was trading at 24,913.35, up 198.30 points at 9.53 am, while Sensex also rallied to 81,233.14, higher by 665.43 points, as expectations of a consumption boost ahead of the festive season lifted sentiment",
            "url": "https://www.thehindubusinessline.com/markets/stock-markets/gst-20-reforms-drive-market-rally-as-nifty-eyes-25000-mark/article70010819.ece",
            "urlToImage": "https://bl-i.thgim.com/public/incoming/vze8e/article70010824.ece/alternates/LANDSCAPE_1200/PO02_Up_arrow.jpg",
            "publishedAt": "2025-09-04T04:45:18Z",
            "content": "Markets opened with strong gains on Thursday morning as the GST Councils landmark tax reforms sparked optimism across sectors. The Nifty 50 started at 24,980.75 from its previous close of 24,715.05 a\u2026 [+4476 chars]"
        },
        {
            "source": {
                "id": null,
                "name": "BusinessLine"
            },
            "author": "Akhil Nallamuthu & BL Research Bureau",
            "title": "Nifty Bank Prediction Today \u2013 September 4, 2025: Nifty Bank futures: Chart indicates bullish intraday trend",
            "description": "Nifty Bank index shows bullish bias with private banks outperforming, Nifty Bank futures may rise to 55,000.",
            "url": "https://www.thehindubusinessline.com/portfolio/technical-analysis/nifty-bank-prediction-today-september-4-2025-nifty-bank-futures-chart-indicates-bullish-intraday-trend/article70010788.ece",
            "urlToImage": "https://bl-i.thgim.com/public/incoming/tmifve/article69659518.ece/alternates/LANDSCAPE_1200/PO01_Chart2.jpg",
            "publishedAt": "2025-09-04T04:20:25Z",
            "content": "Nifty Bank index opened todays session higher at 54,380 compared to yesterdays close of 54,068. It is now hovering around 54,380, up about 0.6 per cent.\r\nThe advance/decline ratio stands at 7/5, show\u2026 [+1146 chars]"
        },
        {
            "source": {
                "id": null,
                "name": "BusinessLine"
            },
            "author": "Akhil Nallamuthu & BL Research Bureau",
            "title": "Nifty Prediction Today \u2013 September 4, 2025: Nifty futures: Likely to gain further",
            "description": "Nifty 50 opens with a gap-up, showing bullish bias; top gainers are Mahindra & Mahindra and Bajaj Finance.",
            "url": "https://www.thehindubusinessline.com/portfolio/technical-analysis/nifty-prediction-today-september-4-2025-nifty-futures-likely-to-gain-further/article70010781.ece",
            "urlToImage": "https://bl-i.thgim.com/public/incoming/jl536m/article69978283.ece/alternates/LANDSCAPE_1200/2025-08-22T174210Z_138941053_RC2R6GA6Z1MO_RTRMADP_3_INDIA-NIFTY-50-REJIG.JPG",
            "publishedAt": "2025-09-04T04:18:13Z",
            "content": "Nifty 50 opened todays session with a gap-up at 24,981 versus yesterdays close of 24,715. It is currently hovering around 24,880, up 0.7 per cent so far today.\r\nThe advance/decline ratio of Nifty 50 \u2026 [+1287 chars]"
        },
        {
            "source": {
                "id": "the-times-of-india",
                "name": "The Times of India"
            },
            "author": "ET Bureau",
            "title": "Compliance with insider trading rules moral responsibility: Sebi chief",
            "description": "Sebi chief Tuhin Kanta Pandey emphasized that banks' management holds a moral responsibility for insider trading compliance, urging stronger internal controls. His remarks follow Sebi's action against IndusInd Bank's former CEO and executives for alleged insi\u2026",
            "url": "https://economictimes.indiatimes.com/markets/stocks/news/compliance-with-insider-trading-rules-moral-responsibility-sebi-chief/articleshow/123687852.cms",
            "urlToImage": "https://img.etimg.com/thumb/msid-123687858,width-1200,height-630,imgsize-13124,overlay-etmarkets/articleshow.jpg",
            "publishedAt": "2025-09-04T00:25:14Z",
            "content": "Mumbai: Sebi chief Tuhin Kanta Pandey on Wednesday said compliance with insider trading rules is a moral responsibility of a bank's management and underscored the need to strengthen the internal cont\u2026 [+1649 chars]"
        },
        {
            "source": {
                "id": "the-times-of-india",
                "name": "The Times of India"
            },
            "author": "Shilpy Sinha and Saloni Shukla",
            "title": "More trouble at IndusInd Bank, ex-CFO seeks removal of board chairman",
            "description": "In a letter to the Prime Minister dated August 26, a copy reviewed by ET, Jain claimed that he uncovered serious issues in treasury operations that had persisted for more than a decade. Jain said he was the only executive to detect the lapses and had fought a\u2026",
            "url": "https://economictimes.indiatimes.com/industry/banking/finance/banking/more-trouble-at-indusind-bank-ex-cfo-seeks-removal-of-board-chairman/articleshow/123684687.cms",
            "urlToImage": "https://img.etimg.com/thumb/msid-123684673,width-1200,height-630,imgsize-1251231,overlay-economictimes/articleshow.jpg",
            "publishedAt": "2025-09-03T19:37:52Z",
            "content": "MUMBAI: In a letter to the Prime Minister dated August 26, a copy reviewed by ET, Jain claimed that he uncovered serious issues in treasury operations that had persisted for more than a decade. Jain \u2026 [+3134 chars]"
        },
        {
            "source": {
                "id": "the-times-of-india",
                "name": "The Times of India"
            },
            "author": "Shilpy Sinha and Saloni Shukla",
            "title": "More trouble at IndusInd Bank, ex-CFO seeks removal of board chairman",
            "description": "In a letter to the Prime Minister dated August 26, a copy reviewed by ET, Jain claimed that he uncovered serious issues in treasury operations that had persisted for more than a decade. Jain said he was the only executive to detect the lapses and had fought a\u2026",
            "url": "https://economictimes.indiatimes.com/industry/banking/finance/banking/more-trouble-at-indusind-bank-ex-cfo-seeks-removal-of-board-chairman/articleshow/123687762.cms",
            "urlToImage": "https://img.etimg.com/thumb/msid-123684673,width-1200,height-630,imgsize-1251231,overlay-etmarkets/articleshow.jpg",
            "publishedAt": "2025-09-03T19:37:52Z",
            "content": "MUMBAI: In a letter to the Prime Minister dated August 26, a copy reviewed by ET, Jain claimed that he uncovered serious issues in treasury operations that had persisted for more than a decade. Jain \u2026 [+3129 chars]"
        },
        {
            "source": {
                "id": null,
                "name": "BusinessLine"
            },
            "author": "BL Mumbai Bureau",
            "title": "SEBI chief asks bank heads to strenghten insider trading compliance",
            "description": "Compliance with insider trading regulations was not just a legal obligation but also a \u201cmoral responsibility,\u201d Tuhin Kanta Pandey said",
            "url": "https://www.thehindubusinessline.com/markets/sebi-chief/article70008432.ece",
            "urlToImage": "https://bl-i.thgim.com/public/incoming/845ykt/article70008560.ece/alternates/LANDSCAPE_1200/20250821123L.jpg",
            "publishedAt": "2025-09-03T13:36:36Z",
            "content": "Securities and Exchange Board of India chairman Tuhin Kanta Pandey stressed on the importance of listed banks putting in place mechanisms to prevent insider trading, saying that they had dual complia\u2026 [+2272 chars]"
        },
        {
            "source": {
                "id": null,
                "name": "BusinessLine"
            },
            "author": "Anupama Ghosh",
            "title": "Metal stocks power markets higher as GST Council expectations drive rally",
            "description": "The turnaround came after a tepid start to the trading session, with metal stocks leading the charge as Tata Steel emerged as the top gainer, soaring 5.96% to \u20b9167.83",
            "url": "https://www.thehindubusinessline.com/markets/metal-stocks-power-markets-higher-as-gst-council-expectations-drive-rally/article70008069.ece",
            "urlToImage": "https://bl-i.thgim.com/public/incoming/kct9/article70008391.ece/alternates/LANDSCAPE_1200/IMG_BL12_Think_percent1_2_1_8AEKC9NV.jpg",
            "publishedAt": "2025-09-03T13:05:50Z",
            "content": "Markets staged a remarkable second-half recovery on Wednesday, with the Sensex surging over 550 points from its session low to close at 80,567.71, gaining 409.83 points or 0.51 per cent, while the Ni\u2026 [+5693 chars]"
        },
        {
            "source": {
                "id": null,
                "name": "BusinessLine"
            },
            "author": "Anupama Ghosh",
            "title": "Metal stocks power markets higher as GST Council expectations drive rally",
            "description": "The turnaround came after a tepid start to the trading session, with metal stocks leading the charge as Tata Steel emerged as the top gainer, soaring 5.96% to \u20b9167.83",
            "url": "https://www.thehindubusinessline.com/markets/stock-markets/metal-stocks-power-markets-higher-as-gst-council-expectations-drive-rally/article70008069.ece",
            "urlToImage": "https://bl-i.thgim.com/public/incoming/kct9/article70008391.ece/alternates/LANDSCAPE_1200/IMG_BL12_Think_percent1_2_1_8AEKC9NV.jpg",
            "publishedAt": "2025-09-03T13:05:50Z",
            "content": "Markets staged a remarkable second-half recovery on Wednesday, with the Sensex surging over 550 points from its session low to close at 80,567.71, gaining 409.83 points or 0.51 per cent, while the Ni\u2026 [+5693 chars]"
        },
        {
            "source": {
                "id": null,
                "name": "BusinessLine"
            },
            "author": "Anupama Ghosh",
            "title": "Metal stocks drive market recovery as Sensex gains 139 points",
            "description": "Metal stocks emerged as the session\u2019s top performers, with Tata Steel surging \u20b97.81 (4.93%) to \u20b9166.20, JSW Steel climbing \u20b934.10 (3.27%) to \u20b91,078.10 and Hindalco advancing \u20b917.95 (2.49%) to \u20b9738.90",
            "url": "https://www.thehindubusinessline.com/markets/stock-markets/metal-stocks-drive-market-recovery-as-sensex-gains-139-points/article70007204.ece",
            "urlToImage": "https://bl-i.thgim.com/public/incoming/9v4lbj/article70007230.ece/alternates/LANDSCAPE_1200/PO16_Rising_chart.jpg",
            "publishedAt": "2025-09-03T07:38:52Z",
            "content": "Markets reversed early losses to trade in positive territory by mid-day on Wednesday, with metal stocks leading the charge as investors awaited outcomes from the ongoing GST Council meeting. \r\nThe Se\u2026 [+2349 chars]"
        },
        {
            "source": {
                "id": null,
                "name": "BusinessLine"
            },
            "author": "Akhil Nallamuthu & BL Research Bureau",
            "title": "Nifty Bank Prediction Today \u2013 September 3, 2025: Nifty Bank futures: Testing a support",
            "description": "Nifty Bank index fluctuates around 53,760, with public sector banks outperforming private peers; futures may decline below 53,950.",
            "url": "https://www.thehindubusinessline.com/portfolio/technical-analysis/nifty-bank-prediction-today-september-3-2025-nifty-bank-futures-testing-a-support/article70006852.ece",
            "urlToImage": "https://bl-i.thgim.com/public/incoming/f5399f/article70002690.ece/alternates/LANDSCAPE_1200/2025-08-22T174210Z_138941053_RC2R6GA6Z1MO_RTRMADP_3_INDIA-NIFTY-50-REJIG.JPG",
            "publishedAt": "2025-09-03T05:29:09Z",
            "content": "Nifty Bank index opened todays session lower at 53,631 compared to Yesterdays close of 53,661. It rose after opening and is now hovering around 53,760, up nearly 0.2 per cent.\r\nThe advance/decline ra\u2026 [+1431 chars]"
        },
        {
            "source": {
                "id": null,
                "name": "BusinessLine"
            },
            "author": "BL Mumbai Bureau",
            "title": "IndusInd Bank appoints Pragati Gondhalekar as head of internal audit",
            "description": "Pragati Gondhalekar\u2019s appointment comes amid a leadership rejig at the private bank, which faced material losses due to accounting discrepancies in derivatives portfolio",
            "url": "https://www.thehindubusinessline.com/money-and-banking/indusind-bank-appoints-pragati-gondhalekar-as-head-of-internal-audit/article70004901.ece",
            "urlToImage": "https://bl-i.thgim.com/public/incoming/xtrkdd/article70004906.ece/alternates/LANDSCAPE_1200/2025-08-05T045421Z_1959791813_RC26KDA2B3IT_RTRMADP_3_INDUSIND-BANK-STOCKS.JPG",
            "publishedAt": "2025-09-02T14:51:30Z",
            "content": "IndusInd Bank has appointed Pragati Gondhalekar as head of internal audit effective September 1, according to an exchange notice. Gondhalekar has over 27 years of global audit and consulting experien\u2026 [+496 chars]"
        },
        {
            "source": {
                "id": null,
                "name": "BusinessLine"
            },
            "author": "BL Mumbai Bureau",
            "title": "IndusInd Bank appoints Pragati Gondhalekar as head of internal audit",
            "description": "Pragati Gondhalekar\u2019s appointment comes amid a leadership rejig at the private bank, which faced material losses due to accounting discrepancies in derivatives portfolio",
            "url": "https://www.thehindubusinessline.com/news/indusind-bank-appoints-pragati-gondhalekar-as-head-of-internal-audit/article70004901.ece",
            "urlToImage": "https://bl-i.thgim.com/public/incoming/xtrkdd/article70004906.ece/alternates/LANDSCAPE_1200/2025-08-05T045421Z_1959791813_RC26KDA2B3IT_RTRMADP_3_INDUSIND-BANK-STOCKS.JPG",
            "publishedAt": "2025-09-02T14:51:30Z",
            "content": "IndusInd Bank has appointed Pragati Gondhalekar as head of internal audit effective September 1, according to an exchange notice. Gondhalekar has over 27 years of global audit and consulting experien\u2026 [+496 chars]"
        },
        {
            "source": {
                "id": null,
                "name": "Livemint"
            },
            "author": "Shivam Shukla",
            "title": "How to foreclose a personal loan offline easily? A step-by-step guide",
            "description": "Offline personal loan foreclosure enables borrowers to repay loans early, reduce interest costs, and complete closure directly at the branch, while understanding foreclosure charges, required documents, and bank procedures.",
            "url": "https://www.livemint.com/money/personal-finance/how-to-foreclose-a-personal-loan-offline-easily-a-step-by-step-guide-11756798226715.html",
            "urlToImage": "https://www.livemint.com/lm-img/img/2025/09/02/1600x900/bank_1750425715587_1756798735652.jpg",
            "publishedAt": "2025-09-02T07:54:25Z",
            "content": "Borrowers aspiring to seek a foreclosure on their personal loan offline can now benefit by following simple steps.\r\nForeclosure basically is the act of repaying the entire loan amount before the sche\u2026 [+4022 chars]"
        },
        {
            "source": {
                "id": "the-times-of-india",
                "name": "The Times of India"
            },
            "author": "ET Online",
            "title": "IndusInd Bank appoints Pragati Gondhalekar as Head \u2013 Internal Audit, Senior Management Personnel",
            "description": "IndusInd Bank has appointed Mrs. Pragati Gondhalekar as Head \u2013 Internal Audit and Senior Management Personnel, effective September 1, 2025. With over 27 years of global audit and consulting experience, she has previously held senior roles at Deutsche Bank, L&\u2026",
            "url": "https://economictimes.indiatimes.com/industry/banking/finance/banking/indusind-bank-appoints-pragati-gondhalekar-as-head-internal-audit-senior-management-personnel/articleshow/123646761.cms",
            "urlToImage": "https://img.etimg.com/thumb/msid-123646749,width-1200,height-630,imgsize-29944,overlay-economictimes/articleshow.jpg",
            "publishedAt": "2025-09-02T03:40:13Z",
            "content": "IndusInd Bank on Monday announced the appointment of Pragati Gondhalekar as Head Internal Audit and part of its Senior Management Personnel, effective September 1, 2025.In a statement to the exchange\u2026 [+774 chars]"
        },
        {
            "source": {
                "id": null,
                "name": "Ndtvprofit.com"
            },
            "author": "NDTV Profit Research",
            "title": "Stocks To Watch: Kotak Mahindra, IndusInd, HDFC Bank, Maruti Suzuki, BEL",
            "description": "Kotak Mahindra Bank Ltd., Bharat Electronics Ltd., HDFC Bank Ltd., Maruti Suzuki India Ltd. and IndusInd Bank Ltd. are some of the stocks that will likely catch investors' attention on Tuesday.",
            "url": "https://www.ndtvprofit.com/markets/stocks-to-watch-today-kotak-mahindra-indusind-hdfc-bank-maruti-suzuki-bel-united-breweries",
            "urlToImage": "https://media.assettype.com/bloombergquint%2F2025-07-16%2Fq4caqo0z%2Fdigital-marketing-data-charts-2025-02-03-10-09-41-utc-1.jpg?rect=0%2C388%2C5472%2C2873&w=1200&auto=format%2Ccompress&ogImage=true",
            "publishedAt": "2025-09-02T01:30:00Z",
            "content": "<li>Kotak Mahindra Bank:\u00a0The Reserve Bank of India has approved the appointment of Paritosh Kashyap as an Executive Director for the bank.\r\n</li><li>Auto Companies: Hero MotoCorp reported total two-w\u2026 [+1586 chars]"
        },
        {
            "source": {
                "id": null,
                "name": "Ndtvprofit.com"
            },
            "author": "Vansh Pansari",
            "title": "All You Need To Know Going Into Trade On Tuesday",
            "description": "The NSE Nifty 50 ended 0.81% higher at 24,625.05 and the BSE Sensex closed 0.7% up at 80,364.49 on Monday. Nifty September Futures up by 0.78% to 24,748 at a premium of 123 points. Nifty September futures open interest up by 0.07%. Nifty Options Sept. 2 Expir\u2026",
            "url": "https://www.ndtvprofit.com/markets/stock-market-today-all-you-need-to-know-going-into-trade-on-september-2-2025",
            "urlToImage": "https://media.assettype.com/bloombergquint%2F2025-08-25%2Fc35blqdm%2Fstock-exchange-market-concept-businessman-trader-2025-01-08-03-45-55-utc.jpg?w=1200&auto=format%2Ccompress&ogImage=true",
            "publishedAt": "2025-09-02T00:30:00Z",
            "content": "<li>Sarveshwar Foods: The company will be opening a rights issue of nearly Rs 150 crore on Sept. 2, with an issue size of 25 crore shares at a price of Rs 6 per share.\r\n</li><li>Kotak Mahindra Bank: \u2026 [+6034 chars]"
        },
        {
            "source": {
                "id": null,
                "name": "BusinessLine"
            },
            "author": "Akhil Nallamuthu & BL Research Bureau",
            "title": "Nifty Bank Prediction Today \u2013 September 1, 2025: Nifty Bank futures: Index faces a resistance",
            "description": "Nifty Bank index opened today\u2019s session flat at 53,658 compared to Friday\u2019s close of 53,656. It rose after opening and is now hovering around 53,850, up 0.4 per cent.",
            "url": "https://www.thehindubusinessline.com/portfolio/technical-analysis/nifty-bank-prediction-today-september-1-2025-nifty-bank-futures-index-faces-a-resistance/article69998751.ece",
            "urlToImage": "https://bl-i.thgim.com/public/incoming/5xz3ws/article69998758.ece/alternates/LANDSCAPE_1200/IMG_Businessman_using_la_2_1_L6DBU8AR.jpg",
            "publishedAt": "2025-09-01T05:02:22Z",
            "content": "Nifty Bank index opened todays session flat at 53,658 compared to Fridays close of 53,656. It rose after opening and is now hovering around 53,850, up 0.4 per cent.\r\nBarring HDFC Bank (down about 0.1\u2026 [+1211 chars]"
        },
        {
            "source": {
                "id": "the-times-of-india",
                "name": "The Times of India"
            },
            "author": "Akash Podishetti",
            "title": "Stocks in news: Ather Energy, Indian Oil, Torrent Power, BHEL, IndusInd Bank",
            "description": "Markets opened with a muted tone, continuing the corrective phase. Ather Energy introduced a new vehicle platform, while CMS Info Systems secured a contract from IPPB for ATM replacement. Indian Oil's SPRINT project is yielding positive results, and Torrent P\u2026",
            "url": "https://economictimes.indiatimes.com/markets/stocks/news/stocks-in-news-ather-energy-indian-oil-torrent-power-bhel-indusind-bank/articleshow/123623508.cms",
            "urlToImage": "https://img.etimg.com/thumb/msid-123623504,width-1200,height-630,imgsize-41494,overlay-etmarkets/articleshow.jpg",
            "publishedAt": "2025-09-01T01:02:56Z",
            "content": "Markets began the new derivatives series on a muted note, extending the prevailing corrective phase. In today's trade, shares of Ather Energy, Indian Oil, Torrent Power, BHEL, IndusInd Bank among oth\u2026 [+1428 chars]"
        },
        {
            "source": {
                "id": null,
                "name": "BusinessLine"
            },
            "author": "BL Mumbai Bureau",
            "title": "IndusInd Bank shareholders reject resolution allowing promoters to appoint 2 directors on board",
            "description": "Shareholders reject IndusInd Bank resolution for nominee directors, CEO appointment approved, stake increase pending RBI approval.",
            "url": "https://www.thehindubusinessline.com/money-and-banking/indusind-bank-shareholders-reject-resolution-allowing-promoters-to-appoint-2-directors-on-board/article69993105.ece",
            "urlToImage": "https://bl-i.thgim.com/public/incoming/x06ivl/article69993116.ece/alternates/LANDSCAPE_1200/2025-07-28T121150Z_1620895313_RC26KDA0OIXR_RTRMADP_3_INDUSIND-BANK-RESULTS.JPG",
            "publishedAt": "2025-08-30T12:26:30Z",
            "content": "Shareholders of IndusInd Bank have rejected a resolution allowing its promoters to appoint two nominee directors on the banks board in the annual general meeting for FY25, according to an exchange no\u2026 [+1097 chars]"
        },
        {
            "source": {
                "id": null,
                "name": "Ndtvprofit.com"
            },
            "author": "Mohammed Uzair Shaikh",
            "title": "IndusInd Bank Shareholders Reject Promoter IIHL's Bid For Two Board Nominees",
            "description": "Shareholders of IndusInd Bank on Friday rejected promoter IndusInd International Holdings Ltd.'s proposal to induct two nominee directors to the board. More than half of the shareholders voted against the IIHL proposal, which required an amendment to the bank\u2026",
            "url": "https://www.ndtvprofit.com/business/indusind-bank-shareholders-reject-promoter-iihls-bid-for-two-board-nominees",
            "urlToImage": "https://media.assettype.com/bloombergquint%2F2024-04%2F85f3dba3-1675-4ec7-ba85-775ef475d129%2FIndusInd_Bank_s_newly_opened_branch_in_Srinagar___Source_Banks_official_facebook_page_.png?w=1200&auto=format%2Ccompress&ogImage=true",
            "publishedAt": "2025-08-30T10:54:20Z",
            "content": "Shareholders of IndusInd Bank on Friday rejected promoter IndusInd International Holdings Ltd.'s proposal to induct two nominee directors to the board.\r\nMore than half of the shareholders voted again\u2026 [+1335 chars]"
        },
        {
            "source": {
                "id": null,
                "name": "BusinessLine"
            },
            "author": "PTI",
            "title": "IndusInd Bank gets promoter IIHL backing as shareholders weigh in on nominee director proposal",
            "description": "The majority shareholders, 54.04%, voted against the amendment in the articles of association of the bank, as per the regulatory filing by IndusInd Bank",
            "url": "https://www.thehindubusinessline.com/money-and-banking/indusind-bank-gets-promoter-iihl-backing-as-shareholders-weigh-in-on-nominee-director-proposal/article69992079.ece",
            "urlToImage": "https://bl-i.thgim.com/public/incoming/mmyfrl/article69992087.ece/alternates/LANDSCAPE_1200/IMG_indusind_2_1_OREAMGCV.jpg",
            "publishedAt": "2025-08-30T04:29:56Z",
            "content": "IndusInd Bank on Friday said its proposal to induct two nominee directors on the private sector lender's board could not get shareholders' approval at the bank's annual general meeting.\r\nThe majority\u2026 [+2299 chars]"
        },
        {
            "source": {
                "id": "the-times-of-india",
                "name": "The Times of India"
            },
            "author": "TNN",
            "title": "IndusInd investors block promoter bid for board seats",
            "description": "India Business News: Mumbai: IndusInd Bank shareholders on Thursday voted down a proposal that would have allowed the promoters to appoint up to two directors on the lende.",
            "url": "https://timesofindia.indiatimes.com/business/india-business/indusind-investors-block-promoter-bid-for-board-seats/articleshow/123594049.cms",
            "urlToImage": "https://static.toiimg.com/thumb/msid-123594054,width-1070,height-580,imgsize-18628,resizemode-75,overlay-toi_sw,pt-32,y_pad-40/photo.jpg",
            "publishedAt": "2025-08-30T01:35:27Z",
            "content": "Heritage, origin and timeless charm: A look at Indian earrings through the ages"
        },
        {
            "source": {
                "id": "the-times-of-india",
                "name": "The Times of India"
            },
            "author": "Saloni Shukla",
            "title": "IndusInd Bank shareholders reject promoters' proposal to induct nominee directors",
            "description": "IndusInd Bank shareholders rejected a resolution allowing the Hinduja Group to appoint two nominee directors, with 54% voting against it. Despite prior approvals from the RBI and the bank's board, concerns raised by proxy advisors led to the proposal's defeat.",
            "url": "https://economictimes.indiatimes.com/industry/banking/finance/banking/indusind-bank-shareholders-reject-promoters-proposal-to-induct-nominee-directors/articleshow/123590361.cms",
            "urlToImage": "https://img.etimg.com/thumb/msid-123590351,width-1200,height-630,imgsize-96882,overlay-economictimes/articleshow.jpg",
            "publishedAt": "2025-08-29T18:00:13Z",
            "content": "Shareholders of IndusInd Bank on Friday voted against a resolution that would have allowed the bank's promoters, the Hinduja Group, to appoint two nominee directors to the board. The proposal was def\u2026 [+2238 chars]"
        },
        {
            "source": {
                "id": "the-times-of-india",
                "name": "The Times of India"
            },
            "author": "Bloomberg",
            "title": "India\u2019s growth surprise may fade with Trump\u2019s 50% tariff hit",
            "description": "India's economic growth surged to 7.8% last quarter, exceeding expectations, fueled by manufacturing and construction. However, concerns rise as US tariffs threaten key sectors like textiles and footwear, potentially impacting jobs and consumption. The rupee \u2026",
            "url": "https://economictimes.indiatimes.com/news/economy/indicators/indias-growth-surprise-may-fade-with-trumps-50-tariff-hit/articleshow/123587309.cms",
            "urlToImage": "https://img.etimg.com/thumb/msid-123587375,width-1200,height-630,imgsize-643702,overlay-economictimes/articleshow.jpg",
            "publishedAt": "2025-08-29T14:53:30Z",
            "content": "Indias surprise pickup in economic growth last quarter comes with rising concern that momentum may fade as US President Donald Trumps 50% tariffs hit the nation.Gross domestic product growth accelera\u2026 [+2987 chars]"
        },
        {
            "source": {
                "id": null,
                "name": "Themorningcontext.com"
            },
            "author": "Furquan Moharkan",
            "title": "The other challenge that Rajiv Anand faces at IndusInd Bank",
            "description": "High levels of attrition, a leadership coterie and allegations of a toxic work culture combine to give the new CEO an HR headache\u2014one that he must tackle with little help from the RBI.",
            "url": "https://themorningcontext.com/business/the-other-challenge-that-rajiv-anand-faces-at-indusind-bank",
            "urlToImage": "https://media2.themorningcontext.com/media/posts_images/IMG_1317.jpg?v=1756449638520",
            "publishedAt": "2025-08-29T05:26:00Z",
            "content": "Subscribe to read this story\r\nWe publish over 500 original, detailed stories every year on startups, corporates, stock markets and economic current affairs.\r\n$99 for one year\r\nAlready have an account\u2026 [+8 chars]"
        },
        {
            "source": {
                "id": "the-times-of-india",
                "name": "The Times of India"
            },
            "author": "Ajay Rag",
            "title": "Banking infrastructure startup TransBnk raises $25 million from Bessemer Venture Partners, others",
            "description": "TransBnk, a banking infrastructure startup, secured $25 million in funding led by Bessemer Venture Partners to fuel its expansion into Southeast Asia and the Middle East. The company aims to enhance its technology and product teams while capitalizing on banks\u2026",
            "url": "https://economictimes.indiatimes.com/tech/funding/banking-infrastructure-startup-transbnk-raises-25-million-from-bessemer-venture-partners-others/articleshow/123551103.cms",
            "urlToImage": "https://img.etimg.com/thumb/width-1200,height-900,imgsize-962541,resizemode-75,msid-123551103/tech/funding/banking-infrastructure-startup-transbnk-raises-25-million-from-bessemer-venture-partners-others.jpg",
            "publishedAt": "2025-08-28T00:30:00Z",
            "content": "Banking infrastructure startup TransBnk has raised $25 million in a funding round led by Bessemer Venture Partners, with participation from Arkam Ventures and Fundamentum Partnership.The investment w\u2026 [+1976 chars]"
        },
        {
            "source": {
                "id": "the-times-of-india",
                "name": "The Times of India"
            },
            "author": "Anupam Nagar",
            "title": "FMCG and auto stocks to outperform even as Nifty loses momentum: Ajit Mishra",
            "description": "Nifty slipped below 24,800 amid banking weakness, sparking concerns of further downside towards 24,600. While sentiment turned negative, FMCG and auto stocks like Maruti, HUL, and Britannia showed resilience. Analysts advise balanced strategies, cautioning on\u2026",
            "url": "https://economictimes.indiatimes.com/markets/stocks/news/fmcg-and-auto-stocks-to-outperform-even-as-nifty-loses-momentum-ajit-mishra/articleshow/123539856.cms",
            "urlToImage": "https://img.etimg.com/thumb/msid-123539841,width-1200,height-630,imgsize-22424,overlay-etmarkets/articleshow.jpg",
            "publishedAt": "2025-08-27T06:16:42Z",
            "content": "After nearly two weeks of rebound, Tuesdays session turned out to be a dampener with selling pressure gripping the indices right from the opening bell.What made it worse was the banking sector, said \u2026 [+2091 chars]"
        },
        {
            "source": {
                "id": "the-times-of-india",
                "name": "The Times of India"
            },
            "author": "Shivendra Kumar",
            "title": "A midcap stock surges up to 22,344% since last Ganesh Chaturthi; 32 others zoom up to 2,557%",
            "description": "Since last Ganesh Chaturthi, 33 stocks delivered significant returns. Elitecon International led with substantial growth. Kothari Industrial Corporation and Colab Platforms also saw major surges. Several other stocks, including Paytm, experienced gains. Nifty\u2026",
            "url": "https://economictimes.indiatimes.com/markets/stocks/news/a-midcap-stock-surges-up-to-22344-since-last-ganesh-chaturthi-32-others-zoom-up-to-2557/articleshow/123539486.cms",
            "urlToImage": "https://img.etimg.com/thumb/msid-123539471,width-1200,height-630,imgsize-43454,overlay-etmarkets/articleshow.jpg",
            "publishedAt": "2025-08-27T05:49:07Z",
            "content": "As India celebrates Ganesh Chaturthi today, a peep into the past one year reveals 33 stocks which have delivered up to a whopping 22,344% returns since the last Ganapati Utsav. At the center of the a\u2026 [+3220 chars]"
        },
        {
            "source": {
                "id": "the-times-of-india",
                "name": "The Times of India"
            },
            "author": "Shivendra Kumar",
            "title": "This midcap, Paytm among 33 stocks that surged up to 22,344% since last Ganesh Chaturthi",
            "description": "As India celebrates Ganesh Chaturthi, a retrospective analysis reveals impressive stock market performances. Over the past year, 33 stocks have delivered remarkable returns, with Elitecon International leading at 22,344%. While the Nifty index experienced flu\u2026",
            "url": "https://economictimes.indiatimes.com/markets/stocks/news/this-midcap-paytm-among-33-stocks-that-surged-up-to-22344-since-last-ganesh-chaturthi/articleshow/123539277.cms",
            "urlToImage": "https://img.etimg.com/thumb/msid-123539260,width-1200,height-630,imgsize-45106,overlay-etmarkets/articleshow.jpg",
            "publishedAt": "2025-08-27T05:37:09Z",
            "content": "As India celebrates Ganesh Chaturthi today, a look back at the past year shows 33 stocks delivering up to 22,000% returns since the last Ganapati Utsav. Topping the list is midcap Elitecon Internatio\u2026 [+3228 chars]"
        },
        {
            "source": {
                "id": null,
                "name": "GlobeNewswire"
            },
            "author": "Research and Markets",
            "title": "India Cards and Payments Market - Opportunities and Risks to 2029",
            "description": "Key opportunities in India's cards and payments market include the growth of real-time payments with UPI Circle, expansion of digital payments in public transport, high digital wallet adoption driven by a young, tech-savvy population, and increased competitio\u2026",
            "url": "https://www.globenewswire.com/news-release/2025/08/26/3139042/28124/en/India-Cards-and-Payments-Market-Opportunities-and-Risks-to-2029.html",
            "urlToImage": "https://ml.globenewswire.com/Resource/Download/908fb457-7f8e-4a08-9081-5565e3dfb3d7",
            "publishedAt": "2025-08-26T08:41:00Z",
            "content": "Dublin, Aug. 26, 2025 (GLOBE NEWSWIRE) -- The \"India Cards and Payments: Opportunities and Risks to 2029\" report has been added to ResearchAndMarkets.com's offering.\r\nThe report provides detailed ana\u2026 [+5800 chars]"
        },
        {
            "source": {
                "id": null,
                "name": "Livemint"
            },
            "author": "Anshika Kayastha, Abirami Sekar",
            "title": "SBI wants to let you pay your bills with keychains",
            "description": "SBI is exploring this capability as debit cards see a significant decline in usage amid wider adoption of UPI and an increase in credit card usage.",
            "url": "https://www.livemint.com/industry/banking/sbi-wants-pay-bills-with-keychains-nfc-cards-debit-card-push-11756043107921.html",
            "urlToImage": "https://www.livemint.com/lm-img/img/2025/08/26/1600x900/SBI_1689004469525_1756169464993.JPG",
            "publishedAt": "2025-08-26T03:30:17Z",
            "content": "Mumbai: If you are a State Bank of India (SBI) customer, get ready to pay for your groceries using keychains. Thats what Indias largest lender wants to try out.\r\nWhile payments have moved much ahead \u2026 [+5344 chars]"
        },
        {
            "source": {
                "id": null,
                "name": "BusinessLine"
            },
            "author": "KS Badri Narayanan",
            "title": "Why these dozen stocks will seek market attention in today\u2019s trade (August 26, 2025)",
            "description": "Corporate announcements: 3M India, Shree Digvijay Cement, Tata Motors, JK Cement, VA Tech Wabag, IndusInd Bank, Ceat, Tolins Tyres, Shree Refrigerations, Future Consumer",
            "url": "https://www.thehindubusinessline.com/markets/why-these-dozen-stocks-will-seek-market-attention-in-todays-trade-august-26-2025/article69977758.ece",
            "urlToImage": "https://bl-i.thgim.com/public/todays-paper/tp-others/ky1f2d/article69969766.ece/alternates/LANDSCAPE_1200/PO24_PG4_ALERTSGATEQAI9M.5.jpg.jpg",
            "publishedAt": "2025-08-26T02:30:32Z",
            "content": "3M India has appointed Aseem Joshi as President and Managing Director (Designate). Joshi brings over 25 years of experience across engineering, consulting, business development, and leadership roles \u2026 [+4483 chars]"
        },
        {
            "source": {
                "id": "the-times-of-india",
                "name": "The Times of India"
            },
            "author": "ETMarkets.com",
            "title": "Stocks in news: Vodafone Idea, Sai Life, BPCL, IndusInd Bank, IREDA",
            "description": "Markets opened positively, fueled by global cues, with several companies in focus due to significant developments. Protean eGov Technologies secured a substantial order from UIDAI, while TGP Asia plans to sell a stake in Sai Life Sciences.",
            "url": "https://economictimes.indiatimes.com/markets/stocks/news/stocks-in-news-vodafone-idea-sai-life-bpcl-indusind-bank-ireda/articleshow/123507341.cms",
            "urlToImage": "https://img.etimg.com/thumb/msid-123507317,width-1200,height-630,imgsize-54812,overlay-etmarkets/articleshow.jpg",
            "publishedAt": "2025-08-26T00:41:00Z",
            "content": "(What's moving Sensex and Nifty Track latest market news, stock tips, Budget 2025, Share Market on Budget 2025 and expert advice, on ETMarkets. Also, ETMarkets.com is now on Telegram. For fastest new\u2026 [+330 chars]"
        },
        {
            "source": {
                "id": "the-times-of-india",
                "name": "The Times of India"
            },
            "author": "ET Bureau",
            "title": "Rajiv Anand takes charge as MD & CEO of IndusInd Bank",
            "description": "Rajiv Anand has officially taken over as the MD & CEO of IndusInd Bank, commencing his three-year term that extends until August 2028. Following his appointment, the previously established 'Committee of Executives' and the 'Oversight Committee of the Board' h\u2026",
            "url": "https://economictimes.indiatimes.com/markets/stocks/news/rajiv-anand-takes-charge-as-md-ceo-of-indusind-bank/articleshow/123513334.cms",
            "urlToImage": "https://img.etimg.com/thumb/msid-123513360,width-1200,height-630,imgsize-7170,overlay-etmarkets/articleshow.jpg",
            "publishedAt": "2025-08-26T00:23:54Z",
            "content": "(What's moving Sensex and Nifty Track latest market news, stock tips, Budget 2025, Share Market on Budget 2025 and expert advice, on ETMarkets. Also, ETMarkets.com is now on Telegram. For fastest new\u2026 [+330 chars]"
        },
        {
            "source": {
                "id": null,
                "name": "BusinessLine"
            },
            "author": "BL Mumbai Bureau",
            "title": "Rajiv Anand takes over as MD, CEO of IndusInd Bank for three years",
            "description": "Rajiv Anand appointed as MD, CEO of IndusInd Bank for three years, focusing on growth and governance.",
            "url": "https://www.thehindubusinessline.com/money-and-banking/rajiv-anand-takes-over-as-md-ceo-of-indusind-bank-for-three-years/article69975951.ece",
            "urlToImage": "https://bl-i.thgim.com/public/incoming/662nrn/article69976069.ece/alternates/LANDSCAPE_1200/BMSMA_17-8-2017_18-35-9_AXISBANK-3.JPG",
            "publishedAt": "2025-08-25T15:00:23Z",
            "content": "Veteran banker and former Axis Bank Deputy MD Rajiv Anand today assumed charge as MD, CEO of IndusInd Bank for a period of three years, according to an exchange filing. businessline was the first to \u2026 [+994 chars]"
        },
        {
            "source": {
                "id": null,
                "name": "Livemint"
            },
            "author": "Jocelyn Fernandes",
            "title": "Rajiv Anand takes charge as MD and CEO of troubled IndusInd Bank",
            "description": "Veteran banker Rajiv Anand takes charge as CEO and MD of private lender IndusInd Bank amid misaccounting troubles.",
            "url": "https://www.livemint.com/industry/banking/rajiv-anand-takes-charge-as-md-ceo-indusind-bank-former-axis-bank-chief-who-is-he-veteran-troubled-private-lender-news-11756121336501.html",
            "urlToImage": "https://images.livemint.com/img/2018/12/24/1600x900/breaking_news_1545650155659.jpg",
            "publishedAt": "2025-08-25T11:43:38Z",
            "content": "Rajiv Anand has taken charge as CEO and MD of IndusInd Bank, the troubled private lender informed the exchanges on August 25.\r\nRajiv Anand's appointment was announced on August 5, when the bank in it\u2026 [+587 chars]"
        },
        {
            "source": {
                "id": "the-times-of-india",
                "name": "The Times of India"
            },
            "author": "ET Online",
            "title": "IndusInd Bank dissolves interim committee as new CEO Rajiv Anand takes charge, says progress made in fixing staff accountability",
            "description": "Rajiv Anand assumes leadership at IndusInd Bank, prompting the dissolution of the interim committee formed after the resignations of the previous CEO and deputy due to misaccounting of derivative trades. The bank has addressed legacy issues and control gaps d\u2026",
            "url": "https://economictimes.indiatimes.com/industry/banking/finance/banking/indusind-bank-dissolves-interim-committee-as-new-ceo-rajiv-anand-takes-charge-says-progress-made-in-fixing-staff-accountability/articleshow/123502200.cms",
            "urlToImage": "https://img.etimg.com/thumb/msid-123502157,width-1200,height-630,imgsize-137828,overlay-economictimes/articleshow.jpg",
            "publishedAt": "2025-08-25T11:21:04Z",
            "content": "As veteran banker Rajiv Anand assumes the role of Chief Executive Officer of IndusInd Bank on Monday, the private lender announced the dissolution of its interim committee. The committee had been for\u2026 [+1326 chars]"
        },
        {
            "source": {
                "id": "the-times-of-india",
                "name": "The Times of India"
            },
            "author": "Reuters",
            "title": "Rajiv Anand takes charge as IndusInd Bank CEO",
            "description": "Rajiv Anand has officially assumed the role of CEO and managing director at IndusInd Bank, as announced in a recent exchange filing. Anand's appointment follows his previous position as deputy managing director at Axis Bank and a career spanning key roles in \u2026",
            "url": "https://economictimes.indiatimes.com/industry/banking/finance/banking/rajiv-anand-takes-charge-as-ceo-of-indias-indusind-bank/articleshow/123500980.cms",
            "urlToImage": "https://img.etimg.com/thumb/msid-123501009,width-1200,height-630,imgsize-1161030,overlay-economictimes/articleshow.jpg",
            "publishedAt": "2025-08-25T10:13:07Z",
            "content": "Investment Ideas\r\nGrow your wealth with stock ideas &amp; sectoral trends.\r\nStock Reports Plus\r\nBuy low &amp; sell high with access to Stock Score, Upside potential &amp; more. \r\nBigBull Portfolio\r\nG\u2026 [+439 chars]"
        },
        {
            "source": {
                "id": "the-times-of-india",
                "name": "The Times of India"
            },
            "author": "ETMarkets.com",
            "title": "IndusInd Bank in focus as CRISIL reaffirms AA+ rating, stock exits Nifty50",
            "description": "IndusInd Bank shares will be in focus after two key developments. CRISIL reaffirmed its long-term ratings at AA+/Negative on the lender\u2019s debt instruments, covering Rs 55 billion worth of bonds, while retaining short-term ratings at A1+. Separately, NSE Indic\u2026",
            "url": "https://economictimes.indiatimes.com/markets/stocks/news/indusind-bank-in-focus-as-crisil-reaffirms-aa-rating-stock-exits-nifty50/articleshow/123493567.cms",
            "urlToImage": "https://img.etimg.com/thumb/msid-123493557,width-1200,height-630,imgsize-29944,overlay-etmarkets/articleshow.jpg",
            "publishedAt": "2025-08-25T03:48:06Z",
            "content": "Shares of IndusInd Bank will be in focus on Monday, August 25, following two key developments. CRISIL Ratings has reaffirmed its AA+ rating on the lenders debt instruments, while the stock has been d\u2026 [+1565 chars]"
        },
        {
            "source": {
                "id": null,
                "name": "BusinessLine"
            },
            "author": "KS Badri Narayanan",
            "title": "Focus will be on NSE indices, FTSE rejig",
            "description": "NSE adds Indigo and Max Healthcare to Nifty 50, while Hindustan Zinc and Mazagon Dock join Nifty Next 50.",
            "url": "https://www.thehindubusinessline.com/markets/focus-will-be-on-nse-indices-ftse-rejig/article69972672.ece",
            "urlToImage": "https://bl-i.thgim.com/public/incoming/ahnf1z/article69971410.ece/alternates/LANDSCAPE_1200/2025-05-26T065309Z_126001537_RC2EPAABSKBU_RTRMADP_3_GROWW-IPO.JPG",
            "publishedAt": "2025-08-25T01:48:16Z",
            "content": "The National Stock Exchange in a latest rejig will add the airline major Interglobe Aviation (Indigo) and the hospital-chain\u00a0Max Healthcare\u00a0into the benchmark Nifty 50 in place of\u00a0IndusInd Bank and t\u2026 [+1340 chars]"
        },
        {
            "source": {
                "id": null,
                "name": "BusinessLine"
            },
            "author": "Team BL, KS Badri Narayanan",
            "title": "Share Market Highlights: Sensex gains 329 points, Nifty near 25,000 as IT stocks rally; rupee ends lower",
            "description": "Sensex, Nifty updates on 25 August 2025: Benchmark indices rebounded on Monday, with the Sensex rising 329 points to 81,635.91 and the Nifty gaining 97.65 points to 24,967.75, tracking global optimism over a potential US Fed rate cut. IT stocks led the rally,\u2026",
            "url": "https://www.thehindubusinessline.com/markets/stock-market-highlights-25th-aug-2025/article69972681.ece",
            "urlToImage": "https://bl-i.thgim.com/public/incoming/j84ntg/article69972677.ece/alternates/LANDSCAPE_1200/IMG_PO27_Markets_2_1_7QEA4EGP.jpg",
            "publishedAt": "2025-08-25T01:21:00Z",
            "content": "<li></li>\r\nAugust 25, 2025 16:16The live blog is now closed.\r\n<li></li>\r\nAugust 25, 2025 16:13Share market live today: Swan Energy Rebrands as Swan Corp, Announces Strategic Focus on High-Growth Sect\u2026 [+70387 chars]"
        },
        {
            "source": {
                "id": null,
                "name": "Karnatakalive.in"
            },
            "author": "",
            "title": "EaseMyTrip targets higher customer retention and growth, deepens marketing tech stack with MoEngage",
            "description": "The company is now set to transition from broad-based digital communication to deeply personalized, one-to-one traveler engagement at scale.",
            "url": "https://www.KarnatakaLive.in//news/easemytrip-targets-higher-customer-retention-and-growth-deepens-marketing-tech-stack-with-moengage20250819115323//",
            "urlToImage": "https://https://aniportalimages.s3.amazonaws.com/media/details/ANI-20250819061724.jpg/",
            "publishedAt": "2025-08-25T00:29:12Z",
            "content": "New Delhi [India], August 19 : EaseMyTrip, one of India's leading travel-tech platforms, today announced a strategic enhancement of its marketing capabilities with the aim of boosting customer retent\u2026 [+2458 chars]"
        },
        {
            "source": {
                "id": null,
                "name": "Andhrapradeshmirror.com"
            },
            "author": "",
            "title": "EaseMyTrip targets higher customer retention and growth, deepens marketing tech stack with MoEngage",
            "description": "The company is now set to transition from broad-based digital communication to deeply personalized, one-to-one traveler engagement at scale.",
            "url": "https://www.AndhraPradeshMirror.com//news/easemytrip-targets-higher-customer-retention-and-growth-deepens-marketing-tech-stack-with-moengage20250819115323//",
            "urlToImage": "https://https://aniportalimages.s3.amazonaws.com/media/details/ANI-20250819061724.jpg/",
            "publishedAt": "2025-08-25T00:27:48Z",
            "content": "New Delhi [India], August 19 : EaseMyTrip, one of India's leading travel-tech platforms, today announced a strategic enhancement of its marketing capabilities with the aim of boosting customer retent\u2026 [+2458 chars]"
        },
        {
            "source": {
                "id": null,
                "name": "Livemint"
            },
            "author": "MintGenie Team",
            "title": "These 6 credit cards provide free access to airport lounges. Check list here",
            "description": "Most credit cards typically have imposed limits to the access to domestic and international lounges by cardholders",
            "url": "https://www.livemint.com/money/personal-finance/these-6-credit-cards-provide-free-access-to-airport-lounges-check-list-here-11755874814760.html",
            "urlToImage": "https://www.livemint.com/lm-img/img/2025/08/22/1600x900/Lounge__1746110286365_1755874979567.jpg",
            "publishedAt": "2025-08-22T16:00:03Z",
            "content": "Credit Cards: If you are a frequent traveller, it is recommended to use a credit card that gives you some cashbacks and reward points against booking a flight ticket or hotel.\r\nAside from these benef\u2026 [+2727 chars]"
        },
        {
            "source": {
                "id": "bloomberg",
                "name": "Bloomberg"
            },
            "author": "Bloomberg",
            "title": "Nifty rejig: IndiGo, Max Healthcare to replace IndusInd Bank, Hero MotoCorp",
            "description": "InterGlobe Aviation may see passive inflow of about $507 million following the rebalance, while Max Healthcare could see buying worth $423 million, estimates Nuvama Institutional Equities",
            "url": "https://www.bloomberg.com/news/articles/2025-08-22/indigo-max-healthcare-set-to-join-india-s-benchmark-nifty-50-index",
            "urlToImage": "https://bl-i.thgim.com/public/incoming/swou2y/article69965773.ece/alternates/LANDSCAPE_1200/2025-06-25T050300Z_629908135_RC23C9AR2B3G_RTRMADP_3_INDIA-NSE-REGULATOR.JPG",
            "publishedAt": "2025-08-22T15:53:03Z",
            "content": "Indias top bourse will add the countrys number one airline company and the most valuable hospital chain by market capitalisation to its benchmark index at the end of September.\u00a0\r\nInterGlobe Aviation \u2026 [+1479 chars]"
        },
        {
            "source": {
                "id": null,
                "name": "Ndtvprofit.com"
            },
            "author": "NDTV Profit Desk",
            "title": "Nifty Rejig: IndiGo, Max Health In, IndusInd Bank And Hero MotoCorp Out",
            "description": "InterGlobe Aviation Ltd., the parent entity of IndiGo, is among the two new inclusions in Nifty 50, the benchmark index of the National Stock Exchange. The other addition is Max Healthcare Institute.",
            "url": "https://www.ndtvprofit.com/markets/nifty-rejig-indigo-max-health-in-indusind-bank-and-hero-motocorp-out",
            "urlToImage": "https://media.assettype.com/bloombergquint%2F2024-01%2F4a567c9e-6a82-4434-b7e4-21e7fd83a2ff%2FWhatsApp_Image_2024_01_25_at_08_54_36.jpeg?rect=0%2C63%2C2970%2C1559&w=1200&auto=format%2Ccompress&ogImage=true",
            "publishedAt": "2025-08-22T15:00:51Z",
            "content": "InterGlobe Aviation Ltd., the parent entity of IndiGo, is among the two new inclusions in Nifty 50, the benchmark index of the National Stock Exchange. The other addition is Max Healthcare Institute \u2026 [+775 chars]"
        },
        {
            "source": {
                "id": null,
                "name": "Economictimes.com"
            },
            "author": "Getty Images",
            "title": "New RBI ATM rules: Free transactions, cash limits and bank charges explained",
            "description": "RBI rules allow customers three free ATM transactions per month in metro cities and five free transactions in non-metro areas. Beyond these, banks can levy charges, with some like HDFC, PNB, and IndusInd already revising their fees, while SBI still follows it\u2026",
            "url": "https://m.economictimes.com/wealth/save/new-rbi-atm-rules-free-transactions-cash-limits-and-bank-charges-explained/free-atm-transactions-sbi-amp-others/slideshow/123451948.cms",
            "urlToImage": "https://img.etimg.com/thumb/msid-123451948,width-1070,height-580,overlay-etwealth/slideshow.jpg",
            "publishedAt": "2025-08-22T09:42:45Z",
            "content": "Aug 22, 2025, 03:29:10 PM IST\r\nRBI rules allow customers three free ATM transactions per month in metro cities and five free transactions in non-metro areas. Beyond these, banks can levy charges, wit\u2026 [+1136 chars]"
        },
        {
            "source": {
                "id": null,
                "name": "Livemint"
            },
            "author": "MintGenie Team",
            "title": "Google Pay joins hands with L&T finance to offer personal loans",
            "description": "Personal loans: This partnership is in line with the NBFC\u2019s product diversification strategy and makes credit more accessible for consumers in a fast, seamless, and digital manner, L&amp;T Finance said in a statement",
            "url": "https://www.livemint.com/money/personal-finance/google-pay-joins-hands-with-l-t-finance-to-offer-personal-loans-11755851188891.html",
            "urlToImage": "https://www.livemint.com/lm-img/img/2025/08/22/1600x900/NEWZEALAND-POLITICS-TECHNOLOGY-0_1728033670350_1755852137288.JPG",
            "publishedAt": "2025-08-22T09:05:22Z",
            "content": "Google Pay has joined with L&amp;T Finance to offer personal loan products to eligible users, the NBFC announced on Thursday.\r\nThis partnership to give\u00a0personal loans is in line with L&amp;T Finance'\u2026 [+1991 chars]"
        },
        {
            "source": {
                "id": null,
                "name": "BusinessLine"
            },
            "author": "Akhil Nallamuthu & BL Research Bureau",
            "title": "Nifty Bank Prediction Today \u2013 August 22, 2025: Nifty Bank futures: Intraday trend can remain bearish",
            "description": "Nifty Bank futures (August) is likely to drop to 55,250 today",
            "url": "https://www.thehindubusinessline.com/portfolio/technical-analysis/nifty-bank-prediction-today-august-22-2025-nifty-bank-futures-intraday-trend-can-remain-bearish/article69963489.ece",
            "urlToImage": "https://bl-i.thgim.com/public/incoming/bl8sqf/article69963516.ece/alternates/LANDSCAPE_1200/PO11_Chart.jpg",
            "publishedAt": "2025-08-22T05:38:34Z",
            "content": "Nifty Bank index opened todays session lower at 55,669 compared to yesterdays close of 55,755. It slipped after opening and is currently trading at 55,250, down 0.9 per cent.\r\nThe advance/decline rat\u2026 [+1463 chars]"
        },
        {
            "source": {
                "id": "the-times-of-india",
                "name": "The Times of India"
            },
            "author": "Nikhil Agarwal",
            "title": "Q1 results led to Asia\u2019s biggest downgrades but 5 brokerages have over 90 stocks in buying list",
            "description": "Despite earlier earnings downgrades, brokerages anticipate a rebound in India Inc's earnings, potentially reaching double-digits after five quarters, fueled by a low base and early Diwali. Opportunities are seen in domestic-focused sectors like financials and\u2026",
            "url": "https://economictimes.indiatimes.com/markets/stocks/news/q1-results-led-to-asias-biggest-downgrades-but-5-brokerages-have-over-90-stocks-in-buying-list/articleshow/123444557.cms",
            "urlToImage": "https://img.etimg.com/thumb/msid-123444538,width-1200,height-630,imgsize-46266,overlay-etmarkets/articleshow.jpg",
            "publishedAt": "2025-08-22T03:30:46Z",
            "content": "Even as India Inc saw Asia's biggest earnings downgrades after a modest Q1 and amid risks from steep US tariffs, brokerages say weak earnings cycle may have bottomed out. Not only will the consumptio\u2026 [+3544 chars]"
        },
        {
            "source": {
                "id": null,
                "name": "Livemint"
            },
            "author": "mint",
            "title": "Mint Explainer | What India Inc\u2019s Q1 results mean for market investors",
            "description": "Despite signs of recovery in certain segments, the Q1 earnings season has painted a bleak picture for many companies in India, with single-digit growth persisting. Here's a look at the winners and losers of the Q1 results season",
            "url": "https://www.livemint.com/companies/company-results/india-inc-q1-fy26-results-q1-fy26-earnings-season-corporate-earnings-india-2025-bse500-companies-11755773668389.html",
            "urlToImage": "https://www.livemint.com/lm-img/img/2025/08/21/1600x900/mkt_1739444446027_1755776553217.png",
            "publishedAt": "2025-08-22T01:30:02Z",
            "content": "The curtains have come down on the earnings season for the first quarter of this financial year. Continued weakness in consumer sentiment, global macroeconomic turbulence and operational headwinds ma\u2026 [+11378 chars]"
        },
        {
            "source": {
                "id": "the-times-of-india",
                "name": "The Times of India"
            },
            "author": "Riya Sharma",
            "title": "Ahead of Market: 10 things that will decide stock market action on Friday",
            "description": "Indian equities closed higher for the sixth straight session, supported by optimism over GST cuts, strength in financials, and Reliance gains. Analysts noted mixed sentiment with profit booking, cautious trading ahead of Jackson Hole, and positive technical s\u2026",
            "url": "https://economictimes.indiatimes.com/markets/stocks/news/ahead-of-market-10-things-that-will-decide-stock-market-action-on-friday/articleshow/123436341.cms",
            "urlToImage": "https://img.etimg.com/thumb/msid-123436330,width-1200,height-630,imgsize-110642,overlay-etmarkets/articleshow.jpg",
            "publishedAt": "2025-08-21T15:54:04Z",
            "content": "The Indian market ended in the green on Thursday, extending its rally to a sixth straight session as optimism over a potential cut in Goods and Services Tax (GST), strength in financials from a propo\u2026 [+4878 chars]"
        },
        {
            "source": {
                "id": null,
                "name": "BusinessLine"
            },
            "author": "Anupama Ghosh",
            "title": "Sensex gains 296 points as markets extend winning run to fifth session",
            "description": "Markets maintained their upward trajectory for the fifth consecutive session on Thursday afternoon, with the Sensex trading 295.58 points higher at 82,153.42 and the Nifty gaining 72.90 points to reach 25,123.45 as of 12.45 PM.",
            "url": "https://www.thehindubusinessline.com/markets/stock-markets/sensex-gains-296-points-as-markets-extend-winning-run-to-fifth-session/article69959352.ece",
            "urlToImage": "https://bl-i.thgim.com/public/incoming/tg4r1g/article69959383.ece/alternates/LANDSCAPE_1200/2025-07-04T063922Z_1738931305_RC2USDAZDY5T_RTRMADP_3_INDIA-BROKERS-STOCKS-JANE-STREET.JPG",
            "publishedAt": "2025-08-21T07:45:35Z",
            "content": "Markets maintained their upward trajectory for the fifth consecutive session on Thursday afternoon, with the Sensex trading 295.58 points higher at 82,153.42 and the Nifty gaining 72.90 points to rea\u2026 [+2244 chars]"
        },
        {
            "source": {
                "id": null,
                "name": "BusinessLine"
            },
            "author": "Anupama Ghosh",
            "title": "Nifty extends winning streak as IT stocks rally, banking sector lags",
            "description": "Leading the gainers on the Nifty 50 are Larsen & Toubro, followed by Bajaj Finserv, SBI Life Insurance Company, Bharat Electronics Limited and Reliance Industries",
            "url": "https://www.thehindubusinessline.com/markets/nifty-extends-winning-streak-as-it-stocks-rally-banking-sector-lags/article69958996.ece",
            "urlToImage": "https://bl-i.thgim.com/public/incoming/3sd8qz/article69958993.ece/alternates/LANDSCAPE_1200/IMG_PO29_Blue_money_2_1_BPEIIEMK.jpg",
            "publishedAt": "2025-08-21T05:28:55Z",
            "content": "Markets opened on a positive note Thursday, with the Nifty 50 starting at 25,142.00 from its previous close of 25,050.55 and trading at 25,122.55, up 72 points or 0.29 per cent, at 10.25 a.m., extend\u2026 [+6203 chars]"
        },
        {
            "source": {
                "id": "the-times-of-india",
                "name": "The Times of India"
            },
            "author": "ETMarkets.com",
            "title": "IndusInd Bank shares in focus after legacy issue resolutions, new leadership appointment",
            "description": "IndusInd Bank's share price is likely to remain in focus as the lender resolves legacy issues in its treasury and microfinance businesses. The board has also cleared the appointment of veteran banker Rajiv Anand as MD & CEO.",
            "url": "https://economictimes.indiatimes.com/markets/stocks/news/indusind-bank-shares-in-focus-after-legacy-issue-resolutions-new-leadership-appointment/articleshow/123421925.cms",
            "urlToImage": "https://img.etimg.com/thumb/msid-123421915,width-1200,height-630,imgsize-24838,overlay-etmarkets/articleshow.jpg",
            "publishedAt": "2025-08-21T02:57:39Z",
            "content": "Shares of IndusInd Bank are likely to be in focus on Thursday, August 21, as the private lender announced significant steps to resolve legacy issues in its treasury and microfinance businesses, repor\u2026 [+2329 chars]"
        },
        {
            "source": {
                "id": null,
                "name": "BusinessLine"
            },
            "author": "Team BL, KS Badri Narayanan",
            "title": "Stock market highlights 21 August 2025: Sensex, Nifty extend winning run to sixth day; buying in ICICI Bank, RIL lifts indices",
            "description": "Sensex, Nifty, Share Price: Stock markets extended their winning run to a sixth consecutive day on Thursday, with benchmark Sensex closing higher by nearly 143 points on buying in blue-chip shares ICICI Bank and Reliance Industries.\nThe 30-share BSE Sensex cl\u2026",
            "url": "https://www.thehindubusinessline.com/markets/share-market-nifty-sensex-highlights-21-august-2025/article69956063.ece",
            "urlToImage": "https://bl-i.thgim.com/public/incoming/aojfqc/article69958721.ece/alternates/LANDSCAPE_1200/stock%20market%20graph.jpg",
            "publishedAt": "2025-08-21T01:32:44Z",
            "content": "<li></li>\r\nAugust 21, 2025 16:31Stock market live updates: Stock markets extend winning run to sixth day; Sensex settles 143 points higher on buying in ICICI Bank, Reliance\r\nStock markets extended th\u2026 [+71123 chars]"
        },
        {
            "source": {
                "id": "the-times-of-india",
                "name": "The Times of India"
            },
            "author": "ETMarkets.com",
            "title": "Stocks in news: IndusInd Bank, India Cements, Godrej Properties, Clean Sciences, Exide Industries",
            "description": "Indian market continues its upward trend. IndusInd Bank addresses past issues. Godrej Properties acquires stake in Godrej Skyline Developers. Promoters may sell stake in Clean Sciences. Exide Industries invests in Exide Energy Solutions. Vedanta informs about\u2026",
            "url": "https://economictimes.indiatimes.com/markets/stocks/news/stocks-in-news-indusind-bank-india-cements-godrej-properties-clean-sciences-exide-industries/articleshow/123414804.cms",
            "urlToImage": "https://img.etimg.com/thumb/msid-123414782,width-1200,height-630,imgsize-47238,overlay-etmarkets/articleshow.jpg",
            "publishedAt": "2025-08-21T00:41:00Z",
            "content": "(What's moving Sensex and Nifty Track latest market news, stock tips, Budget 2025, Share Market on Budget 2025 and expert advice, on ETMarkets. Also, ETMarkets.com is now on Telegram. For fastest new\u2026 [+330 chars]"
        },
        {
            "source": {
                "id": "the-times-of-india",
                "name": "The Times of India"
            },
            "author": "PTI",
            "title": "IndusInd Bank takes decisive steps to address legacy issues of treasury: Chairman",
            "description": "IndusInd Bank addresses legacy issues in treasury and microfinance following past frauds, reporting a net profit of Rs 604 crore this quarter. The bank is reinforcing trust and compliance, focusing on sustainable growth in vehicle finance and retailisation. R\u2026",
            "url": "https://economictimes.indiatimes.com/industry/banking/finance/banking/indusind-bank-takes-decisive-steps-to-address-legacy-issues-of-treasury-chairman/articleshow/123413796.cms",
            "urlToImage": "https://img.etimg.com/thumb/msid-123413818,width-1200,height-630,imgsize-29944,overlay-economictimes/articleshow.jpg",
            "publishedAt": "2025-08-20T15:33:21Z",
            "content": "IndusInd Bank has taken decisive measures to address the identified legacy issues in treasury and microfinance as part of its efforts to come out of the financial mess caused by past frauds, the bank\u2026 [+1847 chars]"
        },
        {
            "source": {
                "id": "the-times-of-india",
                "name": "The Times of India"
            },
            "author": "Riya Sharma",
            "title": "Ahead of Market: 10 things that will decide stock market action on Thursday",
            "description": "Indian markets extended gains for a fifth session on Wednesday, driven by IT stocks and strong domestic inflows. Nifty closed above 25,000 as investors awaited cues from the U.S. Federal Reserve\u2019s Jackson Hole symposium.",
            "url": "https://economictimes.indiatimes.com/markets/stocks/news/ahead-of-market-10-things-that-will-decide-stock-market-action-on-thursday/articleshow/123413464.cms",
            "urlToImage": "https://img.etimg.com/thumb/msid-123413480,width-1200,height-630,imgsize-55920,overlay-etmarkets/articleshow.jpg",
            "publishedAt": "2025-08-20T15:05:05Z",
            "content": "The Indian market ended in the green for a fifth straight day on Wednesday, lifted by IT shares, as investors looked ahead to the Federal Reserves Jackson Hole symposium later this week.The S&amp;P B\u2026 [+3854 chars]"
        },
        {
            "source": {
                "id": null,
                "name": "BusinessLine"
            },
            "author": "Anupama Ghosh",
            "title": "Nifty breaches key 25,000 mark as IT stocks lead fifth straight session gain",
            "description": "Markets rally as Nifty breaks 25,000, boosted by IT and FMCG sectors, with positive sentiment on GST reforms.",
            "url": "https://www.thehindubusinessline.com/markets/nifty-breaches-key-25000-mark-as-it-stocks-lead-fifth-straight-session-gain/article69955762.ece",
            "urlToImage": "https://bl-i.thgim.com/public/incoming/57oo5f/article69955831.ece/alternates/LANDSCAPE_1200/PO30_Bullish_market.jpg",
            "publishedAt": "2025-08-20T12:20:02Z",
            "content": "Markets extended their winning streak for the fifth consecutive trading session on Wednesday, with the Nifty 50 decisively breaking above the crucial 25,000 psychological level, closing at 25,050.55 \u2026 [+4684 chars]"
        },
        {
            "source": {
                "id": "the-times-of-india",
                "name": "The Times of India"
            },
            "author": "Ritesh Presswala",
            "title": "These 5 Nifty stocks drove 80% of Q1FY26 earnings growth. Is it time to Buy?",
            "description": "India\u2019s Nifty50 earnings growth in Q1FY26 was heavily concentrated, with Reliance, Airtel, SBI, HDFC Bank, and ICICI Bank driving 77% of incremental gains. Broader sectors showed mixed performance, though analysts remain optimistic on large-cap stocks\u2019 upside\u2026",
            "url": "https://economictimes.indiatimes.com/markets/stocks/news/these-5-nifty-stocks-drove-80-of-q1fy26-earnings-growth-is-it-time-to-buy/articleshow/123387014.cms",
            "urlToImage": "https://img.etimg.com/thumb/msid-123387076,width-1200,height-630,imgsize-52870,overlay-etmarkets/articleshow.jpg",
            "publishedAt": "2025-08-19T12:03:43Z",
            "content": "Indias equity markets continue to scale new heights, buoyed by investor optimism and robust corporate earnings. However, a deeper look under the hood of the Nifty50 earnings picture paints a more une\u2026 [+3422 chars]"
        },
        {
            "source": {
                "id": "the-times-of-india",
                "name": "The Times of India"
            },
            "author": "Nikhil Agarwal",
            "title": "Smallcap investors just got some bad news from Q1 earnings. Time to tweak your portfolio?",
            "description": "Smallcap investors face headwinds as Q1 earnings reveal an 11% YoY dip, with nearly half of companies missing estimates. Midcaps, however, shine with a robust 24% growth. Experts suggest a portfolio shift towards large-caps and mid-caps, anticipating a strong\u2026",
            "url": "https://economictimes.indiatimes.com/markets/stocks/news/smallcap-investors-just-got-some-bad-news-from-q1-earnings-time-to-tweak-your-portfolio/articleshow/123377454.cms",
            "urlToImage": "https://img.etimg.com/thumb/msid-123377445,width-1200,height-630,imgsize-63230,overlay-etmarkets/articleshow.jpg",
            "publishedAt": "2025-08-19T04:07:47Z",
            "content": "If share prices are slaves to earnings, then the just-concluded Q1 earnings season has just spoiled the outlook for investors in the smallcap basket. According to an analysis by Motilal Oswal, smallc\u2026 [+5394 chars]"
        },
        {
            "source": {
                "id": null,
                "name": "Livemint"
            },
            "author": "Abirami Sekar",
            "title": "Fewer new jobs at top banks. Digital adoption, lower attrition to blame",
            "description": "Experts said branch operations now require fewer people due to wider adoption of digital channels, while much of the hiring done during covid has been absorbed.&nbsp;",
            "url": "https://www.livemint.com/industry/private-bank-hiring-slowdown-private-bank-jobs-india-hdfc-bank-hiring-2025-axis-bank-recruitment-decline-icici-bank-11755412905220.html",
            "urlToImage": "https://www.livemint.com/lm-img/img/2025/08/18/1600x900/g2816fbf9d7ecca205bfef51961a04bdba534c75c6a9a43cbd_1755500985583_1755500985914.jpg",
            "publishedAt": "2025-08-19T00:30:18Z",
            "content": "Mumbai: Hiring across Indias leading private sector banks fell to its lowest in at least three years in FY25 due to a decline in attrition and a major shift to digital banking, showed a Mint analysis\u2026 [+4409 chars]"
        },
        {
            "source": {
                "id": null,
                "name": "BusinessLine"
            },
            "author": "Akhil Nallamuthu & BL Research Bureau",
            "title": "Nifty Bank Prediction Today \u2013 August 18, 2025: Nifty Bank futures: Might consolidate for the rest of the day",
            "description": "Nifty Bank index opens higher, private banks outperforming, futures face resistance at 56,250, support at 55,950.",
            "url": "https://www.thehindubusinessline.com/portfolio/technical-analysis/nifty-bank-prediction-today-august-18-2025-nifty-bank-futures-might-consolidate-for-the-rest-of-the-day/article69946198.ece",
            "urlToImage": "https://bl-i.thgim.com/public/incoming/1qgpy8/article69910056.ece/alternates/LANDSCAPE_1200/2025-07-30T090857Z_314600329_RC2EPAADZ9VJ_RTRMADP_3_NSDL-IPO.JPG",
            "publishedAt": "2025-08-18T05:15:29Z",
            "content": "Nifty Bank index opened todays session with a gap-up at 55,941 compared to last weeks close of 55,342. It moved up after opening and is currently hovering around 56,030, up 1.25 per cent.\r\nAll 12 sto\u2026 [+1434 chars]"
        },
        {
            "source": {
                "id": "the-times-of-india",
                "name": "The Times of India"
            },
            "author": "Sangita Mehta",
            "title": "Axis, Bandhan, Sammaan Capital tweak A/c practices to rewrite books",
            "description": "The revised accounting policy helped Sammaan Capital's report ?661.6 crore gains. In contrast, Axis Bank, which tightened its policy, made additional provisioning of ?614 crore, impacting its earnings. Bandhan Bank implemented procedural changes in the collec\u2026",
            "url": "https://economictimes.indiatimes.com/industry/banking/finance/banking/axis-bandhan-sammaan-capital-tweak-a/c-practices-to-rewrite-books/articleshow/123352811.cms",
            "urlToImage": "https://img.etimg.com/thumb/msid-123350862,width-1200,height-630,imgsize-45384,overlay-etmarkets/articleshow.jpg",
            "publishedAt": "2025-08-17T18:44:52Z",
            "content": "MUMBAI: Axis Bank, Bandhan Bank, and Sammaan Capital have revised their accounting practices in the first quarter of this fiscal year suggesting a mixed approach to accounting prudence.While Axis and\u2026 [+3956 chars]"
        },
        {
            "source": {
                "id": "the-times-of-india",
                "name": "The Times of India"
            },
            "author": "Sangita Mehta",
            "title": "Axis, Bandhan, Sammaan Capital tweak A/c practices to rewrite books",
            "description": "The revised accounting policy helped Sammaan Capital's report ?661.6 crore gains. In contrast, Axis Bank, which tightened its policy, made additional provisioning of ?614 crore, impacting its earnings. Bandhan Bank implemented procedural changes in the collec\u2026",
            "url": "https://economictimes.indiatimes.com/industry/banking/finance/banking/axis-bandhan-sammaan-capital-tweak-a/c-practices-to-rewrite-books/articleshow/123350753.cms",
            "urlToImage": "https://img.etimg.com/thumb/msid-123350862,width-1200,height-630,imgsize-45384,overlay-economictimes/articleshow.jpg",
            "publishedAt": "2025-08-17T18:44:52Z",
            "content": "MUMBAI: Axis Bank, Bandhan Bank, and Sammaan Capital have revised their accounting practices in the first quarter of this fiscal year suggesting a mixed approach to accounting prudence.While Axis and\u2026 [+3957 chars]"
        },
        {
            "source": {
                "id": null,
                "name": "BusinessLine"
            },
            "author": "Kumar Shankar Roy",
            "title": "Low FII holdings mask selective sector buys",
            "description": "Foreign institutional investors in Nifty-500 companies shift focus to specific sectors with growth potential, despite overall decline in ownership.",
            "url": "https://www.thehindubusinessline.com/portfolio/low-fii-holdings-mask-selective-sector-buys/article69941477.ece",
            "urlToImage": "https://bl-i.thgim.com/public/incoming/2on5fv/article69939791.ece/alternates/LANDSCAPE_1200/PO09_Candlestick_graph.jpg",
            "publishedAt": "2025-08-16T16:00:42Z",
            "content": "Foreign institutional investor (FII) ownership in Nifty-500 companies stood at 18.8 per cent in the June 2025 quarter, close to its multi-year lows.\r\nOn surface, the numbers suggest a continued retre\u2026 [+3826 chars]"
        },
        {
            "source": {
                "id": null,
                "name": "Ndtvprofit.com"
            },
            "author": "NDTV Profit Desk",
            "title": "Q1 Results Review: Earnings Cuts Moderating, Says Motilal Oswal; Sees Nifty 50 EPS Growth At 9% In FY26",
            "description": "Motilal Oswal Financial Services Ltd. sees the corporate earnings in the April-June quarter as \"modest but resilient\", which was largely in line with the estimates. \"The Q1FY26 earnings have broadly been in line, with the severity of earnings cuts moderating \u2026",
            "url": "https://www.ndtvprofit.com/quarterly-earnings/q1-results-review-earnings-cuts-moderating-says-motilal-oswal-sees-nifty-50-eps-growth-at-9-in-fy26",
            "urlToImage": "https://media.assettype.com/bloombergquint%2F2024-11-26%2Fneheclwz%2Fforex-trade-graph-chart-concept53876-125167.avif?rect=0%2C20%2C900%2C473&w=1200&auto=format%2Ccompress&ogImage=true",
            "publishedAt": "2025-08-16T15:09:12Z",
            "content": "\"The aggregate earnings of the MOFSL Universe companies grew 11% year-on-year\", versus the brokerage's estimate of 9% rise, according to the note. \r\nExcluding Financials, earnings for the MOFSL Unive\u2026 [+1040 chars]"
        }
    ]
}